<?xml version="1.0" encoding="UTF-8"?>
<!DOCTYPE manifest:manifest PUBLIC "-//OpenOffice.org//DTD Manifest 1.0//EN" "../../../../../../../package/dtd/Manifest.dtd">
<manifest:manifest xmlns:manifest="http://openoffice.org/2001/manifest">
 <manifest:file-entry manifest:full-path="/" manifest:media-type=""/>
 <manifest:file-entry manifest:full-path="O/atevent.xml" manifest:media-type="text/xml"/>
 <manifest:file-entry manifest:full-path="O/O.xml" manifest:media-type="text/xml"/>
 <manifest:file-entry manifest:full-path="A1/atevent.xml" manifest:media-type="text/xml"/>
 <manifest:file-entry manifest:full-path="A1/content.xml" manifest:media-type="text/xml"/>
 <manifest:file-entry manifest:full-path="A1/styles.xml" manifest:media-type="text/xml"/>
 <manifest:file-entry manifest:full-path="A1/" manifest:media-type="application/vnd.oasis.opendocument.text"/>
 <manifest:file-entry manifest:full-path="MVG/atevent.xml" manifest:media-type="text/xml"/>
 <manifest:file-entry manifest:full-path="MVG/content.xml" manifest:media-type="text/xml"/>
 <manifest:file-entry manifest:full-path="MVG/styles.xml" manifest:media-type="text/xml"/>
 <manifest:file-entry manifest:full-path="A2/atevent.xml" manifest:media-type="text/xml"/>
 <manifest:file-entry manifest:full-path="A2/content.xml" manifest:media-type="text/xml"/>
 <manifest:file-entry manifest:full-path="A2/styles.xml" manifest:media-type="text/xml"/>
 <manifest:file-entry manifest:full-path="LIC/atevent.xml" manifest:media-type="text/xml"/>
 <manifest:file-entry manifest:full-path="LIC/content.xml" manifest:media-type="text/xml"/>
 <manifest:file-entry manifest:full-path="LIC/styles.xml" manifest:media-type="text/xml"/>
 <manifest:file-entry manifest:full-path="SOLUIT/atevent.xml" manifest:media-type="text/xml"/>
 <manifest:file-entry manifest:full-path="SOLUIT/content.xml" manifest:media-type="text/xml"/>
 <manifest:file-entry manifest:full-path="SOLUIT/styles.xml" manifest:media-type="text/xml"/>
 <manifest:file-entry manifest:full-path="BO/atevent.xml" manifest:media-type="text/xml"/>
 <manifest:file-entry manifest:full-path="BO/BO.xml" manifest:media-type="text/xml"/>
 <manifest:file-entry manifest:full-path="SOLONT/atevent.xml" manifest:media-type="text/xml"/>
 <manifest:file-entry manifest:full-path="SOLONT/SOLONT.xml" manifest:media-type="text/xml"/>
 <manifest:file-entry manifest:full-path="LOREM/LOREM.xml" manifest:media-type="text/xml"/>
 <manifest:file-entry manifest:full-path="FN/content.xml" manifest:media-type="text/xml"/>
 <manifest:file-entry manifest:full-path="FN/Object_1/settings.xml" manifest:media-type="text/xml"/>
 <manifest:file-entry manifest:full-path="FN/Object_1/content.xml" manifest:media-type="text/xml"/>
 <manifest:file-entry manifest:full-path="FN/Object_1/" manifest:media-type="application/vnd.oasis.opendocument.formula"/>
 <manifest:file-entry manifest:full-path="FN/manifest.rdf" manifest:media-type="application/rdf+xml"/>
 <manifest:file-entry manifest:full-path="FN/styles.xml" manifest:media-type="text/xml"/>
 <manifest:file-entry manifest:full-path="FN/" manifest:media-type="application/vnd.oasis.opendocument.text"/>
 <manifest:file-entry manifest:full-path="BS/BS.xml" manifest:media-type="text/xml"/>
 <manifest:file-entry manifest:full-path="BS/atevent.xml" manifest:media-type="text/xml"/>
 <manifest:file-entry manifest:full-path="SOLAFZ/atevent.xml" manifest:media-type="text/xml"/>
 <manifest:file-entry manifest:full-path="SOLAFZ/content.xml" manifest:media-type="text/xml"/>
 <manifest:file-entry manifest:full-path="SOLAFZ/styles.xml" manifest:media-type="text/xml"/>
 <manifest:file-entry manifest:full-path="BT/atevent.xml" manifest:media-type="text/xml"/>
 <manifest:file-entry manifest:full-path="BT/BT.xml" manifest:media-type="text/xml"/>
 <manifest:file-entry manifest:full-path="A/A.xml" manifest:media-type="text/xml"/>
 <manifest:file-entry manifest:full-path="B/B.xml" manifest:media-type="text/xml"/>
 <manifest:file-entry manifest:full-path="SOL/atevent.xml" manifest:media-type="text/xml"/>
 <manifest:file-entry manifest:full-path="SOL/content.xml" manifest:media-type="text/xml"/>
 <manifest:file-entry manifest:full-path="SOL/styles.xml" manifest:media-type="text/xml"/>
 <manifest:file-entry manifest:full-path="BETV/atevent.xml" manifest:media-type="text/xml"/>
 <manifest:file-entry manifest:full-path="BETV/BETV.xml" manifest:media-type="text/xml"/>
 <manifest:file-entry manifest:full-path="BlockList.xml" manifest:media-type="text/xml"/>
 <manifest:file-entry manifest:full-path="SOLDOC/atevent.xml" manifest:media-type="text/xml"/>
 <manifest:file-entry manifest:full-path="SOLDOC/content.xml" manifest:media-type="text/xml"/>
 <manifest:file-entry manifest:full-path="SOLDOC/styles.xml" manifest:media-type="text/xml"/>
 <manifest:file-entry manifest:full-path="GDH/atevent.xml" manifest:media-type="text/xml"/>
 <manifest:file-entry manifest:full-path="GDH/content.xml" manifest:media-type="text/xml"/>
 <manifest:file-entry manifest:full-path="GDH/styles.xml" manifest:media-type="text/xml"/>
 <manifest:file-entry manifest:full-path="OP/atevent.xml" manifest:media-type="text/xml"/>
 <manifest:file-entry manifest:full-path="OP/content.xml" manifest:media-type="text/xml"/>
 <manifest:file-entry manifest:full-path="OP/styles.xml" manifest:media-type="text/xml"/>
 <manifest:file-entry manifest:full-path="AL/AL.xml" manifest:media-type="text/xml"/>
 <manifest:file-entry manifest:full-path="AL/atevent.xml" manifest:media-type="text/xml"/>
 <manifest:file-entry manifest:full-path="AL/content.xml" manifest:media-type="text/xml"/>
 <manifest:file-entry manifest:full-path="AL/styles.xml" manifest:media-type="text/xml"/>
</manifest:manifest>