<?xml version="1.0" encoding="UTF-8"?>
<!DOCTYPE toolbar:toolbar PUBLIC "-//OpenOffice.org//DTD OfficeDocument 1.0//EN" "toolbar.dtd">
<!--
 * This file is part of the LibreOffice project.
 *
 * This Source Code Form is subject to the terms of the Mozilla Public
 * License, v. 2.0. If a copy of the MPL was not distributed with this
 * file, You can obtain one at http://mozilla.org/MPL/2.0/.
 *
 * This file incorporates work covered by the following license notice:
 *
 *   Licensed to the Apache Software Foundation (ASF) under one or more
 *   contributor license agreements. See the NOTICE file distributed
 *   with this work for additional information regarding copyright
 *   ownership. The ASF licenses this file to you under the Apache
 *   License, Version 2.0 (the "License"); you may not use this file
 *   except in compliance with the License. You may obtain a copy of
 *   the License at http://www.apache.org/licenses/LICENSE-2.0 .
-->
<toolbar:toolbar xmlns:toolbar="http://openoffice.org/2001/toolbar" xmlns:xlink="http://www.w3.org/1999/xlink">
 <toolbar:toolbaritem xlink:href=".uno:DesignerDialog" toolbar:visible="false" toolbar:helpid="5539"/>
 <toolbar:toolbarseparator/>
 <toolbar:toolbaritem xlink:href=".uno:FormatLine" toolbar:helpid="10143"/>
 <toolbar:toolbaritem xlink:href=".uno:LineEndStyle" toolbar:helpid="10301"/>
 <toolbar:toolbarseparator/>
 <toolbar:toolbaritem xlink:href=".uno:XLineStyle" toolbar:helpid="10169"/>
 <toolbar:toolbarseparator/>
 <toolbar:toolbaritem xlink:href=".uno:XLineColor" toolbar:style="dropdown" toolbar:helpid="10172"/>
 <toolbar:toolbaritem xlink:href=".uno:LineWidth" toolbar:helpid="10171"/>
 <toolbar:toolbarseparator/>
 <toolbar:toolbaritem xlink:href=".uno:FormatArea" toolbar:helpid="10142"/>
 <toolbar:toolbarseparator/>
 <toolbar:toolbaritem xlink:href=".uno:FillStyle" toolbar:helpid="10164"/>
 <toolbar:toolbarseparator/>
 <toolbar:toolbaritem xlink:href=".uno:FillShadow" toolbar:helpid="10299"/>
 <toolbar:toolbaritem xlink:href=".uno:ImageMapDialog" toolbar:visible="false" toolbar:helpid="10371"/>
 <toolbar:toolbarseparator/>
 <toolbar:toolbaritem xlink:href=".uno:AdvancedMode" toolbar:style="radio dropdown"/>
 <toolbar:toolbaritem xlink:href=".uno:Mirror" toolbar:visible="false"/>
 <toolbar:toolbaritem xlink:href=".uno:TransformDialog"/>
 <toolbar:toolbaritem xlink:href=".uno:ObjectAlign"/>
 <toolbar:toolbaritem xlink:href=".uno:ObjectPosition"/>
 <toolbar:toolbaritem xlink:href=".uno:DistributeSelection"/>
</toolbar:toolbar>
