<?xml version="1.0" encoding="UTF-8"?>
<manifest:manifest xmlns:manifest="urn:oasis:names:tc:opendocument:xmlns:manifest:1.0" manifest:version="1.3" xmlns:loext="urn:org:documentfoundation:names:experimental:office:xmlns:loext:1.0">
 <manifest:file-entry manifest:full-path="/" manifest:version="1.3" manifest:media-type="application/vnd.oasis.opendocument.presentation-template"/>
 <manifest:file-entry manifest:full-path="styles.xml" manifest:media-type="text/xml"/>
 <manifest:file-entry manifest:full-path="Pictures/1000000000000007000000075D9D31963C8C0E25.jpg" manifest:media-type="image/jpeg"/>
 <manifest:file-entry manifest:full-path="Pictures/1000000000000007000000076677E5BE1EDAF335.jpg" manifest:media-type="image/jpeg"/>
 <manifest:file-entry manifest:full-path="Pictures/1000DC810000A57800007C20AABC768B7E7ACB30.svg" manifest:media-type="image/svg+xml"/>
 <manifest:file-entry manifest:full-path="Pictures/10000000000001920000019230489F7A89351262.jpg" manifest:media-type="image/jpeg"/>
 <manifest:file-entry manifest:full-path="content.xml" manifest:media-type="text/xml"/>
 <manifest:file-entry manifest:full-path="Thumbnails/thumbnail.png" manifest:media-type="image/png"/>
 <manifest:file-entry manifest:full-path="meta.xml" manifest:media-type="text/xml"/>
</manifest:manifest>
