<model>
  <ww8resource name="DopBase" resource="Properties">
    <bitfield size="4" type="U32">
      <bits name="fFacingPages" bits="1" token="rtf:fFacingPages"/>
      <bits name="unused1" bits="1" token="rtf:unused1"/>
      <bits name="fPMHMainDoc" bits="1" token="rtf:fPMHMainDoc"/>
      <bits name="unused2" bits="2" token="rtf:unused2"/>
      <bits name="fpc" bits="2" token="rtf:fpc"/>
      <bits name="unused3" bits="1" token="rtf:unused3"/>
      <bits name="unused4" bits="8" token="rtf:unused4"/>
      <bits name="rncFtn" bits="2" token="rtf:rncFtn"/>
      <bits name="nFtn" bits="14" token="rtf:nFtn"/>
    </bitfield>
    <bitfield size="4" type="U32">
      <bits name="unused5" bits="1" token="rtf:unused5"/>
      <bits name="unused6" bits="1" token="rtf:unused6"/>
      <bits name="unused7" bits="1" token="rtf:unused7"/>
      <bits name="unused8" bits="1" token="rtf:unused8"/>
      <bits name="unused9" bits="1" token="rtf:unused9"/>
      <bits name="unused10" bits="1" token="rtf:unused10"/>
      <bits name="fSplAllDone" bits="1" token="rtf:fSplAllDone"/>
      <bits name="fSplAllClean" bits="1" token="rtf:fSplAllClean"/>
      <bits name="fSplHideErrors" bits="1" token="rtf:fSplHideErrors"/>
      <bits name="fGramHideErrors" bits="1" token="rtf:fGramHideErrors"/>
      <bits name="fLabelDoc" bits="1" token="rtf:fLabelDoc"/>
      <bits name="fHyphCapitals" bits="1" token="rtf:fHyphCapitals"/>
      <bits name="fAutoHyphen" bits="1" token="rtf:fAutoHyphen"/>
      <bits name="fFormNoFields" bits="1" token="rtf:fFormNoFields"/>
      <bits name="fLinkStyles" bits="1" token="rtf:fLinkStyles"/>
      <bits name="fRevMarking" bits="1" token="rtf:fRevMarking"/>
      <bits name="unused11" bits="1" token="rtf:unused11"/>
      <bits name="fExactCWords" bits="1" token="rtf:fExactCWords"/>
      <bits name="fPagHidden" bits="1" token="rtf:fPagHidden"/>
      <bits name="fPagResults" bits="1" token="rtf:fPagResults"/>
      <bits name="fLockAtn" bits="1" token="rtf:fLockAtn"/>
      <bits name="fMirrorMargins" bits="1" token="rtf:fMirrorMargins"/>
      <bits name="fWord97Compat" bits="1" token="rtf:fWord97Compat"/>
      <bits name="unused12" bits="1" token="rtf:unused12"/>
      <bits name="unused13" bits="1" token="rtf:unused13"/>
      <bits name="fProtEnabled" bits="1" token="rtf:fProtEnabled"/>
      <bits name="fDispFormFldSel" bits="1" token="rtf:fDispFormFldSel"/>
      <bits name="fRMView" bits="1" token="rtf:fRMView"/>
      <bits name="fRMPrint" bits="1" token="rtf:fRMPrint"/>
      <bits name="fLockVbaProj" bits="1" token="rtf:fLockVbaProj"/>
      <bits name="fLockRev" bits="1" token="rtf:fLockRev"/>
      <bits name="fEmbedFonts" bits="1" token="rtf:fEmbedFonts"/>
    </bitfield>
    <attribute name="copts60" type="U16" size="2" token="rtf:copts60"/>
    <attribute name="dxaTab" type="U16" size="2" token="rtf:dxaTab"/>
    <attribute name="cpgWebOpt" type="U16" size="2" token="rtf:cpgWebOpt"/>
    <attribute name="dxaHotZ" type="U16" size="2" token="rtf:dxaHotZ"/>
    <attribute name="cConsecHypLim" type="U16" size="2" token="rtf:cConsecHypLim"/>
    <attribute name="wSpare2" type="U16" size="2" token="rtf:wSpare2"/>
    <attribute name="dttmCreated" type="U32" size="4" token="rtf:dttmCreated"/>
    <attribute name="dttmRevised" type="U32" size="4" token="rtf:dttmRevised"/>
    <attribute name="dttmLastPrint" type="U32" size="4" token="rtf:dttmLastPrint"/>
    <attribute name="nRevision" type="U16" size="2" token="rtf:nRevision"/>
    <attribute name="tmEdited" type="U32" size="4" token="rtf:tmEdited"/>
    <attribute name="cWords" type="U32" size="4" token="rtf:cWords"/>
    <attribute name="cCh" type="U32" size="4" token="rtf:cCh"/>
    <attribute name="cPg" type="U16" size="2" token="rtf:cPg"/>
    <attribute name="cParas" type="U32" size="4" token="rtf:cParas"/>
    <bitfield size="4" type="U32">
      <bits name="rncEdn" bits="2" token="rtf:rncEdn"/>
      <bits name="nEdn" bits="14" token="rtf:"/>
      <bits name="epc" bits="2" token="rtf:"/>
      <bits name="unused14" bits="4" token="rtf:unused14"/>
      <bits name="unused15" bits="4" token="rtf:unused15"/>
      <bits name="fPrintFormData" bits="1" token="rtf:fPrintFormData"/>
      <bits name="fSaveFormData" bits="1" token="rtf:fSaveFormData"/>
      <bits name="fShadeFormData" bits="1" token="rtf:fShadeFormData"/>
      <bits name="fShadeMergeFields" bits="1" token="rtf:fShadeMergeFields"/>
      <bits name="reserved2" bits="1" token="rtf:reserved2"/>
      <bits name="fIncludeSubdocsInStats" bits="1" token="rtf:fIncludeSubdocsInStats"/>
    </bitfield>
    <attribute name="cLines" type="U32" size="4" token="rtf:cLines"/>
    <attribute name="cWordsWithSubdocs" type="U32" size="4" token="rtf:cWordsWithSubdocs"/>
    <attribute name="cChWithSubdocs" type="U32" size="4" token="rtf:cChWithSubdocs"/>
    <attribute name="cPgWithSubdocs" type="U16" size="2" token="rtf:cPgWithSubdocs"/>
    <attribute name="cParasWithSubdocs" type="U32" size="4" token="rtf:cParasWithSubdocs"/>
    <attribute name="cLinesWithSubdocs" type="U32" size="4" token="rtf:cLinesWithSubdocs"/>
    <attribute name="lKeyProtDoc" type="U32" size="4" token="rtf:lKeyProtDoc"/>
    <bitfield size="2" type="U16">
      <bits name="wvkoSaved" bits="3" token="rtf:wvkoSaved"/>
      <bits name="pctWwdSaved" bits="9" token="rtf:pctWwdSaved"/>
      <bits name="zkSaved" bits="2" token="rtf:zkSaved"/>
      <bits name="unused16" bits="1" token="rtf:unused16"/>
      <bits name="iGutterPos" bits="1" token="rtf:iGutterPos"/>
    </bitfield>
  </ww8resource>
</model>